borrent_parser/__init__.py
borrent_parser/decoder.py
borrent_parser/encoder.py
borrent_parser-1.0.1.dist-info/LICENSE
borrent_parser-1.0.1.dist-info/METADATA
borrent_parser-1.0.1.dist-info/WHEEL
borrent_parser-1.0.1.dist-info/top_level.txt
borrent_parser-1.0.1.dist-info/RECORD
