Metadata-Version: 2.1
Name: borrent-parser
Version: 1.0.1
Summary: bencode file decoder/encoder
Author: cutlery47
License: MIT
License-File: LICENSE
